xia_scw_instance/__init__.py
xia_scw_instance/instance.cpython-310-darwin.so
xia_scw_instance/templates/ScwInstance/main.tf
xia_scw_instance/templates/ScwInstance/output.tf
xia_scw_instance/templates/ScwInstance/provider.tf
xia_scw_instance/templates/ScwInstance/variables.tf
xia_scw_instance-0.1.3.dist-info/LICENSE.txt
xia_scw_instance-0.1.3.dist-info/METADATA
xia_scw_instance-0.1.3.dist-info/WHEEL
xia_scw_instance-0.1.3.dist-info/top_level.txt
xia_scw_instance-0.1.3.dist-info/RECORD
