Metadata-Version: 2.1
Name: xia-scw-instance
Version: 0.1.3
Summary: X-I-A
Home-page: https://develop.x-i-a.com/docs/xia-scw-instance/0.1.3/index.html
Author: X-I-A
Author-email: admin@x-i-a.com
Requires-Python: >=3.9
License-File: LICENSE.txt
Requires-Dist: xia-fields-scw
Requires-Dist: xia-scw-vpc
